kahi_staff_person/Kahi_staff_person.py
kahi_staff_person/__init__.py
kahi_staff_person/_version.py
Kahi_staff_person-0.1.5.dist-info/LICENSE
Kahi_staff_person-0.1.5.dist-info/METADATA
Kahi_staff_person-0.1.5.dist-info/WHEEL
Kahi_staff_person-0.1.5.dist-info/top_level.txt
Kahi_staff_person-0.1.5.dist-info/RECORD
